isolatr/__init__.py
isolatr-0.1.0.dist-info/LICENSE
isolatr-0.1.0.dist-info/WHEEL
isolatr-0.1.0.dist-info/METADATA
isolatr-0.1.0.dist-info/RECORD
