Metadata-Version: 2.1
Name: isolatr
Version: 0.1.0
Summary: Member group isolation for raid detection.
Home-page: https://github.com/vcokltfre/isolatr
License: MIT
Author: vcokltfre
Author-email: vcokltfre@gmail.com
Requires-Python: >=3.8,<4.0
Classifier: License :: OSI Approved :: MIT License
Classifier: Programming Language :: Python :: 3
Classifier: Programming Language :: Python :: 3.8
Classifier: Programming Language :: Python :: 3.9
Requires-Dist: discord.py (>=1.7.3,<2.0.0)
Project-URL: Repository, https://github.com/vcokltfre/isolatr
